timewise/__init__.py
timewise/big_parent_sample.py
timewise/cli.py
timewise/config_loader.py
timewise/general.py
timewise/parent_sample_base.py
timewise/point_source_utils.py
timewise/utils.py
timewise/wise_bigdata_desy_cluster.py
timewise/wise_data_base.py
timewise/wise_data_by_visit.py
timewise/wise_flux_conversion_correction.dat
timewise-0.5.4.dist-info/METADATA
timewise-0.5.4.dist-info/WHEEL
timewise-0.5.4.dist-info/entry_points.txt
timewise-0.5.4.dist-info/licenses/LICENSE
timewise-0.5.4.dist-info/RECORD
