Metadata-Version: 2.4
Name: timewise
Version: 0.5.4
Summary: A small package to download infrared data from the WISE satellite
License: MIT
License-File: LICENSE
Author: Jannis Necker
Author-email: jannis.necker@gmail.com
Requires-Python: >=3.9,<3.12
Classifier: License :: OSI Approved :: MIT License
Classifier: Programming Language :: Python :: 3
Classifier: Programming Language :: Python :: 3.9
Classifier: Programming Language :: Python :: 3.10
Classifier: Programming Language :: Python :: 3.11
Provides-Extra: dev
Provides-Extra: docs
Requires-Dist: astropy (>=5.1,<6.0.0)
Requires-Dist: backoff (>=2.1.2,<3.0.0)
Requires-Dist: coveralls (>=3.3.1,<4.0.0) ; extra == "dev"
Requires-Dist: jupyter[jupyter] (>=1.0.0,<2.0.0)
Requires-Dist: jupyterlab[jupyter] (>=4.0.6,<5.0.0)
Requires-Dist: matplotlib (>=3.5.3,<4.0.0)
Requires-Dist: myst-parser (>=1,<3) ; extra == "docs"
Requires-Dist: numpy (>=1.23.2,<2.0.0)
Requires-Dist: pandas (>=1.4.3,<3.0.0)
Requires-Dist: pydantic (>=1.9.0,<2.0.0)
Requires-Dist: pytest (>=7.2.2,<8.0.0) ; extra == "dev"
Requires-Dist: pyvo (>=1.7.0,<2.0.0)
Requires-Dist: requests (>=2.28.1,<3.0.0)
Requires-Dist: scikit-image (>=0.19.3,<0.22.0)
Requires-Dist: scikit-learn (>=1.3.0,<2.0.0)
Requires-Dist: seaborn (>=0.11.2,<0.14.0)
Requires-Dist: sphinx-rtd-theme (>=1.3.0,<2.0.0) ; extra == "docs"
Requires-Dist: tqdm (>=4.64.0,<5.0.0)
Requires-Dist: urllib3 (==1.26.15)
Requires-Dist: virtualenv (>=20.16.3,<21.0.0)
Project-URL: Bug Tracker, https://github.com/JannisNe/timewise/issues
Project-URL: Documentation, https://timewise.readthedocs.io/en/latest
Project-URL: Homepage, https://github.com/JannisNe/timewise
